ThymeBoost/Forecaster.py
ThymeBoost/ThymeBoost.py
ThymeBoost/__init__.py
ThymeBoost/cost_functions.py
ThymeBoost/ensemble.py
ThymeBoost/optimizer.py
ThymeBoost/param_iterator.py
ThymeBoost/predict_functions.py
ThymeBoost/split_proposals.py
ThymeBoost/Datasets/__init__.py
ThymeBoost/Datasets/examples.py
ThymeBoost/exogenous_models/__init__.py
ThymeBoost/exogenous_models/decision_tree_exogenous.py
ThymeBoost/exogenous_models/exogenous_base_class.py
ThymeBoost/exogenous_models/glm_exogenous.py
ThymeBoost/exogenous_models/ols_exogenous.py
ThymeBoost/fit_components/__init__.py
ThymeBoost/fit_components/fit_exogenous.py
ThymeBoost/fit_components/fit_seasonality.py
ThymeBoost/fit_components/fit_trend.py
ThymeBoost/fitter/__init__.py
ThymeBoost/fitter/booster.py
ThymeBoost/fitter/decompose.py
ThymeBoost/seasonality_models/__init__.py
ThymeBoost/seasonality_models/classic_seasonality.py
ThymeBoost/seasonality_models/dynamic_fourier_seasonality.py
ThymeBoost/seasonality_models/fourier_seasonality.py
ThymeBoost/seasonality_models/naive_seasonality.py
ThymeBoost/seasonality_models/seasonality_base_class.py
ThymeBoost/trend_models/__init__.py
ThymeBoost/trend_models/arima_trend.py
ThymeBoost/trend_models/butter_filter_trend.py
ThymeBoost/trend_models/croston_trend.py
ThymeBoost/trend_models/decision_tree_trend.py
ThymeBoost/trend_models/ets_trend.py
ThymeBoost/trend_models/ewm_trend.py
ThymeBoost/trend_models/fast_arima_trend.py
ThymeBoost/trend_models/fast_ces_trend.py
ThymeBoost/trend_models/fast_ets_trend.py
ThymeBoost/trend_models/fast_imapa_trend.py
ThymeBoost/trend_models/fast_ses_trend.py
ThymeBoost/trend_models/fast_theta_trend.py
ThymeBoost/trend_models/lbf_trend.py
ThymeBoost/trend_models/linear_trend.py
ThymeBoost/trend_models/loess_trend.py
ThymeBoost/trend_models/mean_trend.py
ThymeBoost/trend_models/median_trend.py
ThymeBoost/trend_models/moving_average_trend.py
ThymeBoost/trend_models/naive_trend.py
ThymeBoost/trend_models/ransac_trend.py
ThymeBoost-0.1.18.dist-info/LICENSE.txt
ThymeBoost-0.1.18.dist-info/METADATA
ThymeBoost-0.1.18.dist-info/WHEEL
ThymeBoost-0.1.18.dist-info/top_level.txt
ThymeBoost-0.1.18.dist-info/RECORD
