Metadata-Version: 2.1
Name: ThymeBoost
Version: 0.1.18
Summary: Gradient boosted time series decomposition for forecasting.
Home-page: https://github.com/tblume1992/ThymeBoost
Author: Tyler Blume
Author-email: t-blume@hotmail.com
Keywords: forecasting,time series,seasonality,trend
Classifier: Programming Language :: Python :: 3
Classifier: License :: OSI Approved :: MIT License
Classifier: Operating System :: OS Independent
License-File: LICENSE.txt
Requires-Dist: numpy
Requires-Dist: pandas
Requires-Dist: statsmodels
Requires-Dist: scikit-learn
Requires-Dist: scipy
Requires-Dist: more-itertools
Requires-Dist: matplotlib
Requires-Dist: tqdm
Requires-Dist: pmdarima
